{
  "date": "2026-05-28",
  "market_summary": "A股5月28日尾盘强势收官：创业板指大涨1.96%、科创50涨1.59%，成长科技股全面领涨。光通信/CPO/光纤三大板块包揽涨幅榜前三，主力资金净流入超280亿元，全市场沪深两市合计成交近3万亿元，市场情绪活跃度明显提升。上证指数仅小涨0.12%，显示主板蓝筹相对滞涨，资金呈明显的结构性分化格局。",
  "intraday_changes": "今日盘中走势呈现标准的科技主升浪形态。早盘光通信板块低开高走，中际旭创开盘1100元（昨收1111元），一度回落至日低1085元后强势拉升，尾盘接近涨停报1197.99元（+7.79%），全天振幅达10.5%，成交额高达329亿元，显示大资金持续加仓。工业富联同样上演'V形反转'，从日低68.89元（开盘70元）拉至75元（+7.02%），成交264亿元创近期新高。\n\n板块轮动特征明显：上午光通信补涨，下午CPO概念接力推升，资金在光通信产业链内部高效流转。寒武纪保持强势涨3.84%报1391.5元，位于日内高位区间。海光信息今日相对偏弱，收跌0.77%报314.36元，日高318.98元未能突破前期阻力；科大讯飞受AI软件板块资金流出影响，跌2.23%报49.13元，收盘位于日低47.91附近，是观察名单中今日最弱个股。整体来看，硬件算力>软件AI，光通信>芯片>AI软件的资金流向格局贯穿全天。",
  "key_insights": [
    "光通信/CPO双板块主力资金净流入合计197.6亿元，为全市场所有题材板块最高，资金高度聚焦光通信产业链，中际旭创、工业富联均站上年内新高区域",
    "创业板指+1.96%、科创50+1.59%远超上证指数+0.12%，成长股与价值股之间今日涨幅差异显著，市场资金显著向科技成长集中",
    "全市场沪深成交合计近3万亿元，为近期高位，液冷概念主力净流入90.3亿、算力概念净流入63.7亿，数据中心净流入43.9亿，AI基础设施主线资金面强劲"
  ],
  "sector_analysis": "AI子板块今日表现可分为三层：【第一层强势】光通信模块(+3.98%)、CPO概念(+3.88%)、光纤概念(+3.69%)，三者主力资金净流入均超80亿，为今日当仁不让的主线；【第二层偏强】液冷概念(+2.19%，净流入90.3亿)、算力概念(+1.50%，净流入63.7亿)、数据中心(+1.62%，净流入43.9亿)，受益于AI基础设施整体景气；【第三层相对落后】半导体概念(+2.53%)和存储芯片(+2.51%)虽有涨幅，但主力分别净流出24.8亿和82.4亿元，出现典型的拉高出货迹象；国产芯片板块净流出30.4亿，华为海思净流出5.1亿，说明资金从芯片设计方向向光通信下游应用方向大幅切换。AIPC净流出6.9亿，AI软件方向（科大讯飞-2.23%）为今日最弱赛道，需警惕短期调整风险。",
  "stock_highlights": [
    {
      "code": "300308",
      "name": "中际旭创",
      "comment": "今日最强龙头，涨幅+7.79%报1197.99元，全天成交额329亿创近期天量，日高1199.79元，距涨停一步之遥。振幅10.5%，资金高度活跃。当前位置接近强阻力区，短线需注意量能是否持续：若明日开盘高于1150元（日内支撑参考低点1085附近）且放量，可继续持有；若高开低走，需警惕大幅回调风险。"
    },
    {
      "code": "601138",
      "name": "工业富联",
      "comment": "服务器/算力基础设施龙头，今日+7.02%报75元，全天成交264亿元，日高76.28元，日低68.89元。今日突破前期阻力区70元后持续上行，尾盘维持在75元强势。支撑位参考68.9-70元（开盘价/前收价区间），若回落至此区间可考虑轻仓介入；阻力位76.28-78元。"
    },
    {
      "code": "688256",
      "name": "寒武纪",
      "comment": "AI芯片龙一，今日+3.84%报1391.5元，日高1404.99元，成交174.7亿。全天基本在日高区间运行，资金未现明显抛压，强势特征保持。当前支撑位参考1349元（日低），阻力位1405-1420元，若明日放量突破1405元可考虑加仓，日内跌破1350元则需减仓观望。"
    },
    {
      "code": "688041",
      "name": "海光信息",
      "comment": "国产高性能CPU龙头，今日偏弱，收跌0.77%报314.36元，开盘311.13元。日高318.98元未能突破前期阻力，日低306.11元。相对同板块的寒武纪表现明显分化，资金今日流向光通信，海光暂被市场边缘化。当前支撑位306-310元，阻力位318-320元。若半导体板块资金轮回，届时可关注310元附近的企稳信号。"
    },
    {
      "code": "300957",
      "name": "新易盛",
      "comment": "光通信核心标的，今日+3.36%报718.34元，日高727元，日低671.77元，成交238亿。开盘即横向整理后拉升，收盘位于日内上半部。阻力位727元（日高），支撑位671-695元（日低/开盘价区域）。光通信主线保持强势背景下短线偏多。"
    },
    {
      "code": "002230",
      "name": "科大讯飞",
      "comment": "AI软件龙头今日表现最弱，跌2.23%报49.13元，日高50.27元（即开盘价），全天单边下行，收盘接近日低47.91元，显示卖压沉重。成交42.7亿，量能偏大说明有资金出逃。短线建议观望，关注50元上方能否重新站稳；若跌破47.5元止损出局。"
    },
    {
      "code": "002138",
      "name": "天孚通信",
      "comment": "光通信模块细分龙头，今日+4.42%报447.56元，日高450.15元，日低409元（振幅达9.8%），成交209.9亿。早盘大幅低开后快速修复并持续上行，尾盘维持在日高附近，资金承接力强。支撑位427-430元（开盘区间），阻力位450-460元，光通信强势延续情况下继续看多。"
    },
    {
      "code": "600487",
      "name": "亨通光电",
      "comment": "光纤/海缆龙头，今日+2.61%报70.48元，日高70.98元，日低65.62元（振幅8.0%），成交109亿。早盘曾回调至65.62，后半段强力反弹，尾盘收复全部失地并创新高。支撑位65.6-67.5元，阻力位71-73元。光纤板块净流入91亿支撑。"
    }
  ],
  "trading_advice": {
    "style": "偏多",
    "position": "60-80%",
    "rationale": "创业板指+1.96%、科创50+1.59%，科技成长股全面领涨；光通信/CPO/液冷三大AI基础设施板块资金净流入合计超370亿元，主力资金方向明确；全市场成交近3万亿元，活跃度达高位。但上证指数仅+0.12%，蓝筹股滞涨；半导体/存储板块主力净流出显示部分题材已被资金轮换。综合判断市场处于结构性牛市格局，科技成长主线清晰，建议维持60-80%仓位，重点持有光通信/CPO/算力产业链个股，回避AI软件/半导体设计方向短线。"
  },
  "afternoon_plan": "尾盘及次日操作建议：\n1. 【持仓策略】光通信核心仓位（中际旭创/天孚通信/新易盛）维持，止损线参考日低区域，中际旭创低于1085元考虑减仓，新易盛低于671元止损；\n2. 【加仓时机】工业富联若明日开盘回踩70-72元获得支撑，可考虑加仓（阻力76.28-78元）；寒武纪若回调至1350-1370元区间且量能萎缩，可轻仓介入，阻力1405元；\n3. 【减仓清仓】科大讯飞今日单边下行，建议减仓或清仓，等待企稳信号（50元以上）再重新评估；海光信息318元阻力未突破，暂不加仓；\n4. 【关注标的】液冷概念（净流入90亿）和算力概念（净流入63.7亿）若个股回调至支撑位可逢低关注；MLCC/被动元件板块今日大涨8.47%，若与AI算力硬件需求逻辑关联则可跟踪；\n5. 【整体仓位】维持60-80%，留20-30%现金应对波动。明日若高开超2%则注意止盈部分，高位震荡时适当降低仓位至50-60%。",
  "risk_warnings": [
    "光通信/CPO板块今日成交量暴增至3000-3300亿级别，短期涨幅过大（中际旭创、天孚通信均有大幅振幅），有高位剧烈震荡或回调风险，追高需严格止损",
    "半导体/存储/国产芯片板块出现主力大幅净流出（存储芯片净流出82亿），涨而不入的资金虹吸现象需警惕，相关个股可能出现'高开低走'",
    "上证指数今日仅涨0.12%，结构性分化若进一步加剧可能引发市场整体情绪逆转，需防范板块快速轮动导致仓位来不及调整的风险",
    "科大讯飞今日单边下跌2.23%，AI软件板块资金面疲弱，持有AI软件类个股需保持警惕，及时设置止损"
  ],
  "hk_us_summary": "港股AI科技股普遍跟随A股情绪偏强，阿里+1.83%、商汤+3.37%表现亮眼，腾讯+0.95%温和上涨；美股前一交易日NVIDIA大涨+5.76%（Blackwell出货超预期），AMD+3.21%，Palantir+2.17%，美国AI硬件板块整体强势，对A股科技股形成积极的外部支撑。注：港美股数据为参考报价，以实际收盘为准。",
  "hk_stocks": [
    {
      "code": "9988.HK",
      "name": "阿里巴巴",
      "price": 116.9,
      "chg": 1.83
    },
    {
      "code": "0700.HK",
      "name": "腾讯",
      "price": 528.5,
      "chg": 0.95
    },
    {
      "code": "3690.HK",
      "name": "美团",
      "price": 198.8,
      "chg": 2.17
    },
    {
      "code": "9999.HK",
      "name": "网易",
      "price": 163.8,
      "chg": -0.73
    },
    {
      "code": "1024.HK",
      "name": "快手",
      "price": 59.2,
      "chg": 1.54
    },
    {
      "code": "0020.HK",
      "name": "商汤",
      "price": 2.15,
      "chg": 3.37
    }
  ],
  "us_stocks": [
    {
      "code": "NVDA",
      "name": "NVIDIA",
      "price": 135.58,
      "chg": 5.76
    },
    {
      "code": "MSFT",
      "name": "Microsoft",
      "price": 463.18,
      "chg": 1.12
    },
    {
      "code": "GOOGL",
      "name": "Alphabet",
      "price": 185.14,
      "chg": 0.88
    },
    {
      "code": "META",
      "name": "Meta",
      "price": 658.42,
      "chg": 1.45
    },
    {
      "code": "AMD",
      "name": "AMD",
      "price": 168.37,
      "chg": 3.21
    },
    {
      "code": "SMCI",
      "name": "SuperMicro",
      "price": 49.71,
      "chg": 4.36
    },
    {
      "code": "PLTR",
      "name": "Palantir",
      "price": 131.22,
      "chg": 2.17
    }
  ],
  "news_highlights": [
    {
      "headline": "光通信/CPO板块今日强势爆发，中际旭创冲击涨停",
      "implication": "AI数据中心算力需求持续爆发推动光通信模块量价齐升，龙头个股主力资金大幅净流入，短中期趋势依然向好"
    },
    {
      "headline": "NVIDIA Blackwell出货超预期，美股NVDA单日大涨5.76%",
      "implication": "AI芯片供应链景气度回升，对A股GPU/算力/光通信相关个股形成正面催化，有助于维持产业链整体热度"
    },
    {
      "headline": "工业富联服务器出货创历史新高，机构上调目标价",
      "implication": "AI服务器需求数据超预期，工业富联今日大涨7%印证基本面改善，AI基础设施投资热情不减"
    },
    {
      "headline": "液冷散热概念资金持续流入，主力净流入90亿元",
      "implication": "AI机房散热需求随算力密度提升快速增长，液冷概念作为算力的重要配套板块，有望持续受到资金关注"
    },
    {
      "headline": "A股全市场成交近3万亿元，市场活跃度大幅提升",
      "implication": "成交量是市场情绪和资金面最直接的指标，3万亿成交量表明存量资金活跃，增量资金持续入场，短期市场继续偏多"
    }
  ],
  "prediction": {
    "label": "明日偏多",
    "confidence": 68,
    "color": "#65a30d",
    "reasons": [
      "创业板指+1.96%、科创50+1.59%尾盘维持强势，科技成长主线明确，上涨动能未明显衰减",
      "光通信/CPO/液冷三大AI基础设施板块主力资金合计净流入超370亿，资金方向坚定，无明显撤退迹象",
      "美股NVDA前夜大涨5.76%，外部正面催化因素明显，对A股隔夜效应有正面提振",
      "全市场成交接近3万亿元高位，市场活跃度高，短线资金做多意愿强烈",
      "风险因素：上证指数涨幅仅0.12%，蓝筹滞涨，结构分化明显；半导体/存储净流出规模较大，需警惕局部高位回调"
    ]
  }
}