{
  "fetch_time": "2026-06-15 00:15:54 UTC",
  "fetch_date": "2026-06-15",
  "report_type": "morning",
  "expected_data_date": "2026-06-12",
  "data_source_note": "实时行情API在本环境被网络策略封锁，数据来源于2026-06-12早盘快照（10:01 AM北京时间）",
  "indices": {
    "shanghai": {
      "price": 4031.13,
      "chg": 1.11,
      "amount": 495194415084.0,
      "name": "上证指数",
      "data_date": "2026-06-12"
    },
    "shenzhen": {
      "price": 15055.16,
      "chg": 1.37,
      "amount": 557289196761.5,
      "name": "深证成指",
      "data_date": "2026-06-12"
    },
    "chinext": {
      "price": 3873.48,
      "chg": 1.63,
      "amount": 273624492076.51,
      "name": "创业板指",
      "data_date": "2026-06-12"
    },
    "star50": {
      "price": 1711.78,
      "chg": 2.97,
      "amount": 59362246618.0,
      "name": "科创50",
      "data_date": "2026-06-12"
    }
  },
  "index_technicals": {
    "shanghai": {
      "price": 4031.13,
      "chg_pct": 1.11,
      "ma5": 3996.148,
      "ma10": 4028.307,
      "ma20": 4074.769,
      "ma_trend": "空头排列",
      "rsi_12": 40.05,
      "macd": null,
      "macd_signal": null,
      "macd_hist": null,
      "macd_status": "未知",
      "volume_ratio": 0.36,
      "volume_label": "缩量",
      "divergence": false,
      "support_20d": 3927.85,
      "resistance_20d": 4199.53,
      "score": 20,
      "score_label": "★",
      "name": "上证指数"
    },
    "shenzhen": {
      "price": 15055.16,
      "chg_pct": 1.37,
      "ma5": 14990.228,
      "ma10": 15256.361,
      "ma20": 15449.228,
      "ma_trend": "空头排列",
      "rsi_12": 38.5,
      "macd": null,
      "macd_signal": null,
      "macd_hist": null,
      "macd_status": "未知",
      "volume_ratio": 0.34,
      "volume_label": "缩量",
      "divergence": false,
      "support_20d": 14681.64,
      "resistance_20d": 16047.41,
      "score": 20,
      "score_label": "★",
      "name": "深证成指"
    },
    "chinext": {
      "price": 3873.48,
      "chg_pct": 1.63,
      "ma5": 3862.612,
      "ma10": 3948.968,
      "ma20": 3963.804,
      "ma_trend": "空头排列",
      "rsi_12": 42.16,
      "macd": null,
      "macd_signal": null,
      "macd_hist": null,
      "macd_status": "未知",
      "volume_ratio": 0.36,
      "volume_label": "缩量",
      "divergence": false,
      "support_20d": 3755.61,
      "resistance_20d": 4218.33,
      "score": 20,
      "score_label": "★",
      "name": "创业板指"
    },
    "star50": {
      "price": 1711.78,
      "chg_pct": 2.97,
      "ma5": 1657.224,
      "ma10": 1677.294,
      "ma20": 1740.988,
      "ma_trend": "空头排列",
      "rsi_12": 40.78,
      "macd": null,
      "macd_signal": null,
      "macd_hist": null,
      "macd_status": "未知",
      "volume_ratio": 0.5,
      "volume_label": "缩量",
      "divergence": true,
      "support_20d": 1578.18,
      "resistance_20d": 1901.97,
      "score": 12,
      "score_label": "★",
      "name": "科创50"
    }
  },
  "watchlist_technicals": [
    {
      "name": "中际旭创",
      "code": "300308",
      "sector": "光通信/CPO/光模块",
      "ticker": "300308.SZ",
      "close": 1150.65,
      "chg_pct": 2.37,
      "open": 1182.0,
      "high": 1188.5,
      "low": 1146.88,
      "prev_close": 1124.01,
      "volume": 114107,
      "amount": 13305364487.51,
      "data_date": "2026-06-12(盘中)",
      "ma5": 1151.328,
      "ma10": 1181.344,
      "ma20": 1131.164,
      "ma_trend": "震荡偏多",
      "macd": null,
      "macd_signal": null,
      "macd_hist": null,
      "macd_status": "未知",
      "rsi_12": 53.66,
      "volume_ratio": 0.33,
      "volume_label": "缩量",
      "support_20d": 988.88,
      "resistance_20d": 1320.0,
      "score": 40,
      "score_label": "★",
      "divergence": true
    },
    {
      "name": "新易盛",
      "code": "300502",
      "sector": "光通信/CPO/光模块",
      "ticker": "300502.SZ",
      "close": 516.23,
      "chg_pct": -1.86,
      "open": 540.0,
      "high": 544.98,
      "low": 514.8,
      "prev_close": 526.01,
      "volume": 223245,
      "amount": 11737853951.71,
      "data_date": "2026-06-12(盘中)",
      "ma5": 534.192,
      "ma10": 533.383,
      "ma20": 495.332,
      "ma_trend": "多头排列",
      "macd": null,
      "macd_signal": null,
      "macd_hist": null,
      "macd_status": "未知",
      "rsi_12": 54.17,
      "volume_ratio": 0.53,
      "volume_label": "缩量",
      "support_20d": 399.51,
      "resistance_20d": 583.84,
      "score": 52,
      "score_label": "★",
      "divergence": false
    },
    {
      "name": "天孚通信",
      "code": "300394",
      "sector": "光通信/CPO/光模块",
      "ticker": "300394.SZ",
      "close": 294.52,
      "chg_pct": 0.18,
      "open": 303.02,
      "high": 305.0,
      "low": 291.2,
      "prev_close": 293.99,
      "volume": 160977,
      "amount": 4787303983.26,
      "data_date": "2026-06-12(盘中)",
      "ma5": 300.278,
      "ma10": 315.654,
      "ma20": 298.702,
      "ma_trend": "震荡偏空",
      "macd": null,
      "macd_signal": null,
      "macd_hist": null,
      "macd_status": "未知",
      "rsi_12": 46.85,
      "volume_ratio": 0.4,
      "volume_label": "缩量",
      "support_20d": 239.49,
      "resistance_20d": 374.5,
      "score": 40,
      "score_label": "★",
      "divergence": false
    },
    {
      "name": "工业富联",
      "code": "601138",
      "sector": "AI服务器",
      "ticker": "601138.SS",
      "close": 71.1,
      "chg_pct": 2.27,
      "open": 71.94,
      "high": 72.18,
      "low": 71.03,
      "prev_close": 69.52,
      "volume": 479377,
      "amount": 3432781310.0,
      "data_date": "2026-06-12(盘中)",
      "ma5": 71.394,
      "ma10": 74.439,
      "ma20": 72.075,
      "ma_trend": "震荡偏空",
      "macd": null,
      "macd_signal": null,
      "macd_hist": null,
      "macd_status": "未知",
      "rsi_12": 51.42,
      "volume_ratio": 0.25,
      "volume_label": "缩量",
      "support_20d": 64.5,
      "resistance_20d": 84.95,
      "score": 30,
      "score_label": "★",
      "divergence": true
    },
    {
      "name": "中科曙光",
      "code": "603019",
      "sector": "AI服务器",
      "ticker": "603019.SS",
      "close": 82.3,
      "chg_pct": 1.14,
      "open": 83.0,
      "high": 83.43,
      "low": 82.08,
      "prev_close": 81.37,
      "volume": 113448,
      "amount": 938764631.0,
      "data_date": "2026-06-12(盘中)",
      "ma5": 81.056,
      "ma10": 82.979,
      "ma20": 88.531,
      "ma_trend": "空头排列",
      "macd": null,
      "macd_signal": null,
      "macd_hist": null,
      "macd_status": "未知",
      "rsi_12": 30.13,
      "volume_ratio": 0.27,
      "volume_label": "缩量",
      "support_20d": 77.77,
      "resistance_20d": 101.22,
      "score": 20,
      "score_label": "★",
      "divergence": false
    },
    {
      "name": "寒武纪",
      "code": "688256",
      "sector": "半导体设备/制造/AI芯片",
      "ticker": "688256.SS",
      "close": 1232.46,
      "chg_pct": 1.06,
      "open": 1258.0,
      "high": 1260.0,
      "low": 1220.91,
      "prev_close": 1219.53,
      "volume": 36891,
      "amount": 4563450974.0,
      "data_date": "2026-06-12(盘中)",
      "ma5": 1240.666,
      "ma10": 1277.753,
      "ma20": 1305.599,
      "ma_trend": "强势空头",
      "macd": null,
      "macd_signal": null,
      "macd_hist": null,
      "macd_status": "未知",
      "rsi_12": 40.33,
      "volume_ratio": 0.31,
      "volume_label": "缩量",
      "support_20d": 1175.0,
      "resistance_20d": 1448.01,
      "score": 20,
      "score_label": "★",
      "divergence": false
    },
    {
      "name": "海光信息",
      "code": "688041",
      "sector": "半导体设备/制造/AI芯片",
      "ticker": "688041.SS",
      "close": 291.5,
      "chg_pct": 0.57,
      "open": 299.82,
      "high": 299.84,
      "low": 290.7,
      "prev_close": 289.85,
      "volume": 141320,
      "amount": 4167433610.0,
      "data_date": "2026-06-12(盘中)",
      "ma5": 278.804,
      "ma10": 279.866,
      "ma20": 297.317,
      "ma_trend": "空头排列",
      "macd": null,
      "macd_signal": null,
      "macd_hist": null,
      "macd_status": "未知",
      "rsi_12": 38.51,
      "volume_ratio": 0.35,
      "volume_label": "缩量",
      "support_20d": 255.84,
      "resistance_20d": 345.0,
      "score": 12,
      "score_label": "★",
      "divergence": false
    },
    {
      "name": "长飞光纤",
      "code": "601869",
      "sector": "光纤光缆",
      "ticker": "601869.SS",
      "close": 441.24,
      "chg_pct": -0.29,
      "open": 456.51,
      "high": 456.51,
      "low": 432.51,
      "prev_close": 442.52,
      "volume": 46908,
      "amount": 2076007938.0,
      "data_date": "2026-06-12(盘中)",
      "ma5": 452.214,
      "ma10": 438.394,
      "ma20": 411.657,
      "ma_trend": "多头排列",
      "macd": null,
      "macd_signal": null,
      "macd_hist": null,
      "macd_status": "未知",
      "rsi_12": 64.74,
      "volume_ratio": 0.27,
      "volume_label": "缩量",
      "support_20d": 351.37,
      "resistance_20d": 495.0,
      "score": 52,
      "score_label": "★",
      "divergence": false
    },
    {
      "name": "亨通光电",
      "code": "600487",
      "sector": "光纤光缆",
      "ticker": "600487.SS",
      "close": 100.17,
      "chg_pct": -2.18,
      "open": 105.08,
      "high": 105.49,
      "low": 98.5,
      "prev_close": 102.4,
      "volume": 647045,
      "amount": 6522387631.0,
      "data_date": "2026-06-12(盘中)",
      "ma5": 101.988,
      "ma10": 95.404,
      "ma20": 83.958,
      "ma_trend": "多头排列",
      "macd": null,
      "macd_signal": null,
      "macd_hist": null,
      "macd_status": "未知",
      "rsi_12": 79.8,
      "volume_ratio": 0.29,
      "volume_label": "缩量",
      "support_20d": 65.62,
      "resistance_20d": 109.99,
      "score": 60,
      "score_label": "★★",
      "divergence": false
    },
    {
      "name": "科大讯飞",
      "code": "002230",
      "sector": "其他",
      "ticker": "002230.SZ",
      "close": 40.87,
      "chg_pct": 0.2,
      "open": 41.2,
      "high": 41.38,
      "low": 40.39,
      "prev_close": 40.79,
      "volume": 173213,
      "amount": 706612040.29,
      "data_date": "2026-06-12(盘中)",
      "ma5": 42.516,
      "ma10": 44.936,
      "ma20": 46.747,
      "ma_trend": "强势空头",
      "macd": null,
      "macd_signal": null,
      "macd_hist": null,
      "macd_status": "未知",
      "rsi_12": 14.42,
      "volume_ratio": 0.38,
      "volume_label": "缩量",
      "support_20d": 40.39,
      "resistance_20d": 50.99,
      "score": 12,
      "score_label": "★",
      "divergence": false
    }
  ],
  "sectors": [
    {
      "sector": "AI服务器",
      "avg_chg": 1.71,
      "up": 2,
      "down": 0,
      "total": 2,
      "leader": {
        "name": "工业富联",
        "code": "601138",
        "chg_pct": 2.27
      },
      "laggard": {
        "name": "中科曙光",
        "code": "603019",
        "chg_pct": 1.14
      },
      "avg_score": 25.0,
      "avg_volume_ratio": 0.26,
      "stocks": [
        {
          "code": "601138",
          "name": "工业富联",
          "chg_pct": 2.27,
          "score": 30
        },
        {
          "code": "603019",
          "name": "中科曙光",
          "chg_pct": 1.14,
          "score": 20
        }
      ],
      "note": "(样本不完整，仅含部分成分股)"
    },
    {
      "sector": "半导体设备/制造/AI芯片",
      "avg_chg": 0.81,
      "up": 2,
      "down": 0,
      "total": 2,
      "leader": {
        "name": "寒武纪",
        "code": "688256",
        "chg_pct": 1.06
      },
      "laggard": {
        "name": "海光信息",
        "code": "688041",
        "chg_pct": 0.57
      },
      "avg_score": 16.0,
      "avg_volume_ratio": 0.33,
      "stocks": [
        {
          "code": "688256",
          "name": "寒武纪",
          "chg_pct": 1.06,
          "score": 20
        },
        {
          "code": "688041",
          "name": "海光信息",
          "chg_pct": 0.57,
          "score": 12
        }
      ],
      "note": "(样本不完整，仅含部分成分股)"
    },
    {
      "sector": "光通信/CPO/光模块",
      "avg_chg": 0.23,
      "up": 2,
      "down": 1,
      "total": 3,
      "leader": {
        "name": "中际旭创",
        "code": "300308",
        "chg_pct": 2.37
      },
      "laggard": {
        "name": "新易盛",
        "code": "300502",
        "chg_pct": -1.86
      },
      "avg_score": 44.0,
      "avg_volume_ratio": 0.42,
      "stocks": [
        {
          "code": "300308",
          "name": "中际旭创",
          "chg_pct": 2.37,
          "score": 40
        },
        {
          "code": "300394",
          "name": "天孚通信",
          "chg_pct": 0.18,
          "score": 40
        },
        {
          "code": "300502",
          "name": "新易盛",
          "chg_pct": -1.86,
          "score": 52
        }
      ],
      "note": "(样本不完整，仅含部分成分股)"
    },
    {
      "sector": "光纤光缆",
      "avg_chg": -1.24,
      "up": 0,
      "down": 2,
      "total": 2,
      "leader": {
        "name": "长飞光纤",
        "code": "601869",
        "chg_pct": -0.29
      },
      "laggard": {
        "name": "亨通光电",
        "code": "600487",
        "chg_pct": -2.18
      },
      "avg_score": 56.0,
      "avg_volume_ratio": 0.28,
      "stocks": [
        {
          "code": "601869",
          "name": "长飞光纤",
          "chg_pct": -0.29,
          "score": 52
        },
        {
          "code": "600487",
          "name": "亨通光电",
          "chg_pct": -2.18,
          "score": 60
        }
      ],
      "note": "(样本不完整，仅含部分成分股)"
    }
  ],
  "hk_stocks": [],
  "us_stocks": [],
  "is_friday": false,
  "data_freshness": {
    "expected_date": "2026-06-12",
    "quote_date_mode": "2026-06-12(盘中快照)",
    "stale_quote_count": 0,
    "yf_history_ok": false,
    "hk_count": 0,
    "us_count": 0,
    "data_limitation": "所有实时行情接口（新浪/腾讯/Yahoo/Stooq）均被网络白名单封锁，本报告使用2026-06-12早盘10:01 AM数据，指数数据截至当日收盘（当时尚在交易中）"
  },
  "board_capital_flows": [
    {
      "f2": 1469.54,
      "f3": 1.53,
      "f4": 22.1,
      "f5": 148838616,
      "f6": 461312392398.0,
      "f12": "BK0821",
      "f14": "MSCI中国",
      "f20": 81624436736000,
      "f62": 14026936320.0,
      "f66": 13700390912.0,
      "f69": 2.97,
      "f72": 326545408.0,
      "f75": 0.07,
      "f78": -11391213568.0,
      "f81": -2.47,
      "f84": -2629902336.0,
      "f87": -0.57,
      "f104": 449,
      "f105": 107,
      "f184": 3.04
    },
    {
      "f2": 3161.06,
      "f3": 1.31,
      "f4": 40.79,
      "f5": 390311460,
      "f6": 952010323552.0,
      "f12": "BK0596",
      "f14": "融资融券",
      "f20": 120204107776000,
      "f62": 13943193600.0,
      "f66": 14708551680.0,
      "f69": 1.55,
      "f72": -765358080.0,
      "f75": -0.08,
      "f78": -15933820928.0,
      "f81": -1.68,
      "f84": 2051473408.0,
      "f87": 0.22,
      "f104": 2967,
      "f105": 741,
      "f184": 1.47
    },
    {
      "f2": 1077.75,
      "f3": 2.56,
      "f4": 26.89,
      "f5": 13695026,
      "f6": 301602108563.0,
      "f12": "BK1059",
      "f14": "百元股",
      "f20": 25996987648000,
      "f62": 12599177216.0,
      "f66": 10514587648.0,
      "f69": 3.49,
      "f72": 2084589568.0,
      "f75": 0.69,
      "f78": -8598556672.0,
      "f81": -2.85,
      "f84": -3982444544.0,
      "f87": -1.32,
      "f104": 206,
      "f105": 51,
      "f184": 4.18
    },
    {
      "f2": 999.34,
      "f3": 1.51,
      "f4": 14.87,
      "f5": 96828503,
      "f6": 322488390404.0,
      "f12": "BK1663",
      "f14": "大盘股",
      "f20": 72669507584000,
      "f62": 9873010688.0,
      "f66": 9888194560.0,
      "f69": 3.07,
      "f72": -15183872.0,
      "f75": 0.0,
      "f78": -8670228480.0,
      "f81": -2.69,
      "f84": -1194950400.0,
      "f87": -0.37,
      "f104": 233,
      "f105": 60,
      "f184": 3.06
    },
    {
      "f2": 3107.83,
      "f3": 1.5,
      "f4": 45.83,
      "f5": 77758518,
      "f6": 345087811293.0,
      "f12": "BK0917",
      "f14": "半导体概念",
      "f20": 19621617920000,
      "f62": 8672473088.0,
      "f66": 7366533120.0,
      "f69": 2.14,
      "f72": 1305939968.0,
      "f75": 0.38,
      "f78": -7852781568.0,
      "f81": -2.28,
      "f84": -857371904.0,
      "f87": -0.25,
      "f104": 347,
      "f105": 140,
      "f184": 2.52
    },
    {
      "f2": 1009.53,
      "f3": 2.27,
      "f4": 22.38,
      "f5": 37918333,
      "f6": 243286895313.0,
      "f12": "BK1713",
      "f14": "科技风格",
      "f20": 22299512320000,
      "f62": 8055151616.0,
      "f66": 8411724800.0,
      "f69": 3.46,
      "f72": -356573184.0,
      "f75": -0.15,
      "f78": -6383976960.0,
      "f81": -2.63,
      "f84": -1664059904.0,
      "f87": -0.68,
      "f104": 79,
      "f105": 21,
      "f184": 3.31
    },
    {
      "f2": 2557.27,
      "f3": 1.26,
      "f4": 31.82,
      "f5": 190481862,
      "f6": 443829539856.0,
      "f12": "BK0707",
      "f14": "沪股通",
      "f20": 74714247168000,
      "f62": 7995150336.0,
      "f66": 7109140480.0,
      "f69": 1.6,
      "f72": 886009856.0,
      "f75": 0.2,
      "f78": -9269772288.0,
      "f81": -2.09,
      "f84": 1278701568.0,
      "f87": 0.29,
      "f104": 1178,
      "f105": 313,
      "f184": 1.8
    },
    {
      "f2": 3150.49,
      "f3": 2.35,
      "f4": 72.47,
      "f5": 23353742,
      "f6": 151108729988.0,
      "f12": "BK1137",
      "f14": "存储芯片",
      "f20": 8118726912000,
      "f62": 7073352192.0,
      "f66": 6295468800.0,
      "f69": 4.17,
      "f72": 777883392.0,
      "f75": 0.52,
      "f78": -5901547264.0,
      "f81": -3.91,
      "f84": -1171106560.0,
      "f87": -0.78,
      "f104": 89,
      "f105": 29,
      "f184": 4.69
    },
    {
      "f2": 1748.46,
      "f3": 1.69,
      "f4": 29.1,
      "f5": 43814979,
      "f6": 232068089328.0,
      "f12": "BK1005",
      "f14": "专精特新",
      "f20": 14638426112000,
      "f62": 6990339072.0,
      "f66": 4208715776.0,
      "f69": 1.82,
      "f72": 2781623296.0,
      "f75": 1.2,
      "f78": -5145776128.0,
      "f81": -2.22,
      "f84": -1750416128.0,
      "f87": -0.75,
      "f104": 1030,
      "f105": 214,
      "f184": 3.01
    },
    {
      "f2": 5058.1,
      "f3": 1.6,
      "f4": 79.51,
      "f5": 60903603,
      "f6": 252715296514.0,
      "f12": "BK0891",
      "f14": "国产芯片",
      "f20": 16872730624000,
      "f62": 6493043200.0,
      "f66": 6660426240.0,
      "f69": 2.64,
      "f72": -167383040.0,
      "f75": -0.07,
      "f78": -6592733184.0,
      "f81": -2.61,
      "f84": 115265280.0,
      "f87": 0.05,
      "f104": 284,
      "f105": 84,
      "f184": 2.57
    },
    {
      "f2": 1447.66,
      "f3": 1.28,
      "f4": 18.3,
      "f5": 95724594,
      "f6": 303926755566.0,
      "f12": "BK0568",
      "f14": "深成500",
      "f20": 30986332928000,
      "f62": 6435822080.0,
      "f66": 7994112512.0,
      "f69": 2.63,
      "f72": -1558290432.0,
      "f75": -0.51,
      "f78": -5675745280.0,
      "f81": -1.87,
      "f84": -760073472.0,
      "f87": -0.25,
      "f104": 383,
      "f105": 102,
      "f184": 2.12
    },
    {
      "f2": 1257.99,
      "f3": 1.19,
      "f4": 14.85,
      "f5": 210057698,
      "f6": 499363938615.0,
      "f12": "BK0804",
      "f14": "深股通",
      "f20": 43175586816000,
      "f62": 6283730944.0,
      "f66": 8480632832.0,
      "f69": 1.7,
      "f72": -2196901888.0,
      "f75": -0.44,
      "f78": -7305314304.0,
      "f81": -1.46,
      "f84": 1021583360.0,
      "f87": 0.2,
      "f104": 1312,
      "f105": 355,
      "f184": 1.26
    },
    {
      "f2": 12003.52,
      "f3": 1.11,
      "f4": 132.23,
      "f5": 88765957,
      "f6": 253767881133.0,
      "f12": "BK0500",
      "f14": "HS300_",
      "f20": 67617235712000,
      "f62": 6153181184.0,
      "f66": 6679185408.0,
      "f69": 2.63,
      "f72": -526004224.0,
      "f75": -0.21,
      "f78": -5693769728.0,
      "f81": -2.24,
      "f84": -458650624.0,
      "f87": -0.18,
      "f104": 221,
      "f105": 70,
      "f184": 2.42
    },
    {
      "f2": 940.42,
      "f3": 1.47,
      "f4": 13.66,
      "f5": 60163535,
      "f6": 224992034910.0,
      "f12": "BK1677",
      "f14": "2025年报预增",
      "f20": 19005676800000,
      "f62": 5588134912.0,
      "f66": 5316873472.0,
      "f69": 2.37,
      "f72": 271261440.0,
      "f75": 0.12,
      "f78": -4298341888.0,
      "f81": -1.91,
      "f84": -1243211776.0,
      "f87": -0.55,
      "f104": 522,
      "f105": 97,
      "f184": 2.49
    },
    {
      "f2": 4518.68,
      "f3": 1.83,
      "f4": 81.28,
      "f5": 24207211,
      "f6": 112671201261.0,
      "f12": "BK0877",
      "f14": "PCB",
      "f20": 5922592512000,
      "f62": 5530660864.0,
      "f66": 4227514624.0,
      "f69": 3.76,
      "f72": 1303146240.0,
      "f75": 1.16,
      "f78": -2656080896.0,
      "f81": -2.36,
      "f84": -2868713216.0,
      "f87": -2.55,
      "f104": 111,
      "f105": 41,
      "f184": 4.91
    },
    {
      "f2": 990.64,
      "f3": 1.67,
      "f4": 16.25,
      "f5": 80698327,
      "f6": 240410687792.0,
      "f12": "BK1664",
      "f14": "中盘股",
      "f20": 20163253248000,
      "f62": 5456194304.0,
      "f66": 4800846336.0,
      "f69": 2.0,
      "f72": 655347968.0,
      "f75": 0.27,
      "f78": -4049887232.0,
      "f81": -1.69,
      "f84": -1398866688.0,
      "f87": -0.58,
      "f104": 403,
      "f105": 86,
      "f184": 2.27
    },
    {
      "f2": 1105.18,
      "f3": 2.52,
      "f4": 27.15,
      "f5": 16746739,
      "f6": 153959647430.0,
      "f12": "BK1665",
      "f14": "大盘成长",
      "f20": 15892021760000,
      "f62": 5307465728.0,
      "f66": 6516733696.0,
      "f69": 4.24,
      "f72": -1209267968.0,
      "f75": -0.79,
      "f78": -4155023616.0,
      "f81": -2.7,
      "f84": -1145135360.0,
      "f87": -0.74,
      "f104": 66,
      "f105": 12,
      "f184": 3.45
    },
    {
      "f2": 1680.68,
      "f3": 0.89,
      "f4": 14.9,
      "f5": 196997733,
      "f6": 336720853788.0,
      "f12": "BK0879",
      "f14": "标准普尔",
      "f20": 65009986304000,
      "f62": 4714122752.0,
      "f66": 6054522368.0,
      "f69": 1.8,
      "f72": -1340399616.0,
      "f75": -0.4,
      "f78": -6769086464.0,
      "f81": -2.01,
      "f84": 2059710464.0,
      "f87": 0.61,
      "f104": 768,
      "f105": 236,
      "f184": 1.4
    },
    {
      "f2": 1717.59,
      "f3": 1.23,
      "f4": 20.82,
      "f5": 50099664,
      "f6": 133122022029.0,
      "f12": "BK0612",
      "f14": "上证180_",
      "f20": 49352352256000,
      "f62": 4639479296.0,
      "f66": 3648269312.0,
      "f69": 2.74,
      "f72": 991209984.0,
      "f75": 0.74,
      "f78": -4218098176.0,
      "f81": -3.17,
      "f84": -420590080.0,
      "f87": -0.32,
      "f104": 134,
      "f105": 41,
      "f184": 3.49
    },
    {
      "f2": 1762.12,
      "f3": 0.91,
      "f4": 15.92,
      "f5": 229521972,
      "f6": 492677750931.0,
      "f12": "BK0867",
      "f14": "富时罗素",
      "f20": 74158469120000,
      "f62": 4508332032.0,
      "f66": 8042881024.0,
      "f69": 1.63,
      "f72": -3534548992.0,
      "f75": -0.72,
      "f78": -7600046080.0,
      "f81": -1.54,
      "f84": 3097829376.0,
      "f87": 0.63,
      "f104": 949,
      "f105": 289,
      "f184": 0.92
    },
    {
      "f2": 2553.21,
      "f3": 1.45,
      "f4": 36.58,
      "f5": 76988240,
      "f6": 221760990695.0,
      "f12": "BK0701",
      "f14": "中证500",
      "f20": 19192711680000,
      "f62": 4396717312.0,
      "f66": 4530565376.0,
      "f69": 2.05,
      "f72": -133848064.0,
      "f75": -0.06,
      "f78": -4678009856.0,
      "f81": -2.11,
      "f84": 286028032.0,
      "f87": 0.13,
      "f104": 399,
      "f105": 84,
      "f184": 1.98
    },
    {
      "f2": 2206.0,
      "f3": 1.31,
      "f4": 28.58,
      "f5": 51178955,
      "f6": 224621080279.0,
      "f12": "BK0714",
      "f14": "5G概念",
      "f20": 16075723776000,
      "f62": 4027680512.0,
      "f66": 5055519232.0,
      "f69": 2.25,
      "f72": -1027838720.0,
      "f75": -0.46,
      "f78": -2565072640.0,
      "f81": -1.14,
      "f84": -1429462272.0,
      "f87": -0.64,
      "f104": 224,
      "f105": 93,
      "f184": 1.79
    },
    {
      "f2": 2122.55,
      "f3": 1.54,
      "f4": 32.24,
      "f5": 59018100,
      "f6": 167643280493.0,
      "f12": "BK1090",
      "f14": "机器人概念",
      "f20": 14438097152000,
      "f62": 3772094208.0,
      "f66": 3727192576.0,
      "f69": 2.23,
      "f72": 44901632.0,
      "f75": 0.03,
      "f78": -4210393088.0,
      "f81": -2.51,
      "f84": 477309440.0,
      "f87": 0.29,
      "f104": 582,
      "f105": 112,
      "f184": 2.25
    },
    {
      "f2": 2600.75,
      "f3": 1.36,
      "f4": 34.87,
      "f5": 66139222,
      "f6": 182187644605.0,
      "f12": "BK0900",
      "f14": "新能源车",
      "f20": 16667378688000,
      "f62": 3721251072.0,
      "f66": 3761054976.0,
      "f69": 2.07,
      "f72": -39803904.0,
      "f75": -0.02,
      "f78": -3082442240.0,
      "f81": -1.69,
      "f84": -653885440.0,
      "f87": -0.36,
      "f104": 536,
      "f105": 135,
      "f184": 2.04
    },
    {
      "f2": 1975.89,
      "f3": 1.26,
      "f4": 24.52,
      "f5": 77466843,
      "f6": 273950083922.0,
      "f12": "BK0742",
      "f14": "创业板综",
      "f20": 20384507904000,
      "f62": 3629920000.0,
      "f66": 3900571392.0,
      "f69": 1.42,
      "f72": -270651392.0,
      "f75": -0.1,
      "f78": -3037683712.0,
      "f81": -1.11,
      "f84": -592236032.0,
      "f87": -0.22,
      "f104": 1064,
      "f105": 258,
      "f184": 1.33
    },
    {
      "f2": 2435.66,
      "f3": 1.48,
      "f4": 35.43,
      "f5": 17965101,
      "f6": 63038416516.0,
      "f12": "BK1178",
      "f14": "AI眼镜",
      "f20": 4091818880000,
      "f62": 3605042688.0,
      "f66": 3191032576.0,
      "f69": 5.07,
      "f72": 414010112.0,
      "f75": 0.66,
      "f78": -3436315648.0,
      "f81": -5.46,
      "f84": -171092480.0,
      "f87": -0.27,
      "f104": 102,
      "f105": 18,
      "f184": 5.73
    },
    {
      "f2": 15260.76,
      "f3": 2.15,
      "f4": 321.92,
      "f5": 10656900,
      "f6": 139487063558.0,
      "f12": "BK0536",
      "f14": "基金重仓",
      "f20": 9629221632000,
      "f62": 3534102272.0,
      "f66": 4493011200.0,
      "f69": 3.22,
      "f72": -958908928.0,
      "f75": -0.69,
      "f78": -3674512128.0,
      "f81": -2.63,
      "f84": 140740864.0,
      "f87": 0.1,
      "f104": 79,
      "f105": 20,
      "f184": 2.53
    },
    {
      "f2": 935.1,
      "f3": 1.09,
      "f4": 10.08,
      "f5": 44505021,
      "f6": 98017204676.0,
      "f12": "BK1639",
      "f14": "周期股",
      "f20": 23697890048000,
      "f62": 3472112640.0,
      "f66": 3141273600.0,
      "f69": 3.21,
      "f72": 330839040.0,
      "f75": 0.34,
      "f78": -2915874816.0,
      "f81": -2.98,
      "f84": -555939072.0,
      "f87": -0.57,
      "f104": 76,
      "f105": 21,
      "f184": 3.55
    },
    {
      "f2": 1124.28,
      "f3": 1.24,
      "f4": 13.76,
      "f5": 56464890,
      "f6": 258831558753.0,
      "f12": "BK1650",
      "f14": "通信技术",
      "f20": 16616975104000,
      "f62": 3459625728.0,
      "f66": 4943008512.0,
      "f69": 1.91,
      "f72": -1483382784.0,
      "f75": -0.57,
      "f78": -2301661184.0,
      "f81": -0.89,
      "f84": -1179472640.0,
      "f87": -0.46,
      "f104": 271,
      "f105": 106,
      "f184": 1.34
    },
    {
      "f2": 84565.25,
      "f3": 2.32,
      "f4": 1915.49,
      "f5": 42117214,
      "f6": 99508423401.0,
      "f12": "BK0490",
      "f14": "军工",
      "f20": 6480353280000,
      "f62": 3404830976.0,
      "f66": 3243394304.0,
      "f69": 3.26,
      "f72": 161436672.0,
      "f75": 0.16,
      "f78": -1776923904.0,
      "f81": -1.79,
      "f84": -1512562688.0,
      "f87": -1.52,
      "f104": 352,
      "f105": 64,
      "f184": 3.42
    },
    {
      "f2": 9175.49,
      "f3": 1.22,
      "f4": 110.35,
      "f5": 44707953,
      "f6": 106314464138.0,
      "f12": "BK0499",
      "f14": "AH股",
      "f20": 42766627840000,
      "f62": 3402142464.0,
      "f66": 3170875904.0,
      "f69": 2.99,
      "f72": 231266560.0,
      "f75": 0.22,
      "f78": -3406464512.0,
      "f81": -3.21,
      "f84": 3743488.0,
      "f87": 0.0,
      "f104": 147,
      "f105": 35,
      "f184": 3.2
    },
    {
      "f2": 1068.25,
      "f3": 2.18,
      "f4": 22.74,
      "f5": 29306093,
      "f6": 143021359808.0,
      "f12": "BK1669",
      "f14": "中盘成长",
      "f20": 8834848000000,
      "f62": 3396007680.0,
      "f66": 2087876096.0,
      "f69": 1.46,
      "f72": 1308131584.0,
      "f75": 0.92,
      "f78": -1897208064.0,
      "f81": -1.33,
      "f84": -1488334336.0,
      "f87": -1.04,
      "f104": 156,
      "f105": 28,
      "f184": 2.38
    },
    {
      "f2": 939.67,
      "f3": 1.66,
      "f4": 15.3,
      "f5": 29546584,
      "f6": 91871048022.0,
      "f12": "BK1661",
      "f14": "行业龙头",
      "f20": 30798206208000,
      "f62": 3271375360.0,
      "f66": 3369796608.0,
      "f69": 3.67,
      "f72": -98421248.0,
      "f75": -0.11,
      "f78": -2399906048.0,
      "f81": -2.61,
      "f84": -871043072.0,
      "f87": -0.95,
      "f104": 74,
      "f105": 20,
      "f184": 3.56
    },
    {
      "f2": 2787.3,
      "f3": 1.93,
      "f4": 52.91,
      "f5": 7193989,
      "f6": 41746838374.0,
      "f12": "BK1164",
      "f14": "AIPC",
      "f20": 2286343408000,
      "f62": 2963601408.0,
      "f66": 2577279488.0,
      "f69": 6.18,
      "f72": 386321920.0,
      "f75": 0.93,
      "f78": -2731195136.0,
      "f81": -6.55,
      "f84": -226641152.0,
      "f87": -0.54,
      "f104": 40,
      "f105": 7,
      "f184": 7.11
    },
    {
      "f2": 1019.8,
      "f3": 1.6,
      "f4": 16.07,
      "f5": 16721125,
      "f6": 72709338912.0,
      "f12": "BK1680",
      "f14": "2026一季报预增",
      "f20": 4780026112000,
      "f62": 2815217664.0,
      "f66": 1778642176.0,
      "f69": 2.45,
      "f72": 1036575488.0,
      "f75": 1.43,
      "f78": -1535343616.0,
      "f81": -2.11,
      "f84": -1278380032.0,
      "f87": -1.76,
      "f104": 92,
      "f105": 16,
      "f184": 3.88
    },
    {
      "f2": 5946.83,
      "f3": 1.55,
      "f4": 91.02,
      "f5": 30861205,
      "f6": 77079095496.0,
      "f12": "BK0666",
      "f14": "苹果概念",
      "f20": 6013840640000,
      "f62": 2799405056.0,
      "f66": 2822115840.0,
      "f69": 3.67,
      "f72": -22710784.0,
      "f75": -0.03,
      "f78": -2023719168.0,
      "f81": -2.63,
      "f84": -782054144.0,
      "f87": -1.02,
      "f104": 98,
      "f105": 29,
      "f184": 3.64
    },
    {
      "f2": 2839.96,
      "f3": 2.18,
      "f4": 60.69,
      "f5": 4775187,
      "f6": 48198672906.0,
      "f12": "BK1152",
      "f14": "高带宽内存",
      "f20": 2246693600000,
      "f62": 2648121344.0,
      "f66": 2220115200.0,
      "f69": 4.61,
      "f72": 428006144.0,
      "f75": 0.89,
      "f78": -1864944384.0,
      "f81": -3.87,
      "f84": -793721424.0,
      "f87": -1.65,
      "f104": 19,
      "f105": 9,
      "f184": 5.5
    },
    {
      "f2": 2801.96,
      "f3": 1.75,
      "f4": 48.1,
      "f5": 17628172,
      "f6": 103058802620.0,
      "f12": "BK0935",
      "f14": "中芯概念",
      "f20": 4734153728000,
      "f62": 2605753088.0,
      "f66": 2710961920.0,
      "f69": 2.63,
      "f72": -105208832.0,
      "f75": -0.1,
      "f78": -2158376448.0,
      "f81": -2.1,
      "f84": -502378240.0,
      "f87": -0.49,
      "f104": 46,
      "f105": 20,
      "f184": 2.53
    },
    {
      "f2": 4818.96,
      "f3": 0.95,
      "f4": 45.18,
      "f5": 197246415,
      "f6": 281870056219.0,
      "f12": "BK0683",
      "f14": "央国企改革",
      "f20": 52272166656000,
      "f62": 2586412544.0,
      "f66": 3402790400.0,
      "f69": 1.21,
      "f72": -816377856.0,
      "f75": -0.29,
      "f78": -3956121600.0,
      "f81": -1.4,
      "f84": 1378923520.0,
      "f87": 0.49,
      "f104": 1066,
      "f105": 311,
      "f184": 0.92
    },
    {
      "f2": 1108.83,
      "f3": 1.09,
      "f4": 11.91,
      "f5": 33265186,
      "f6": 99120377027.0,
      "f12": "BK1646",
      "f14": "消费电子概念",
      "f20": 5732730368000,
      "f62": 2558213632.0,
      "f66": 2921315328.0,
      "f69": 2.95,
      "f72": -363101696.0,
      "f75": -0.37,
      "f78": -3225226752.0,
      "f81": -3.26,
      "f84": 664191744.0,
      "f87": 0.67,
      "f104": 138,
      "f105": 42,
      "f184": 2.58
    },
    {
      "f2": 1689.15,
      "f3": 1.64,
      "f4": 27.26,
      "f5": 10561306,
      "f6": 51223730081.0,
      "f12": "BK0969",
      "f14": "汽车芯片",
      "f20": 2339150880000,
      "f62": 2553244160.0,
      "f66": 2199589376.0,
      "f69": 4.3,
      "f72": 353654784.0,
      "f75": 0.69,
      "f78": -2390459392.0,
      "f81": -4.67,
      "f84": -162202624.0,
      "f87": -0.32,
      "f104": 54,
      "f105": 15,
      "f184": 4.99
    },
    {
      "f2": 2090.64,
      "f3": 2.77,
      "f4": 56.31,
      "f5": 23156634,
      "f6": 50235776980.0,
      "f12": "BK0808",
      "f14": "军民融合",
      "f20": 3499981376000,
      "f62": 2495124224.0,
      "f66": 2252033280.0,
      "f69": 4.48,
      "f72": 243090944.0,
      "f75": 0.48,
      "f78": -1263531776.0,
      "f81": -2.52,
      "f84": -1149723136.0,
      "f87": -2.29,
      "f104": 151,
      "f105": 25,
      "f184": 4.97
    },
    {
      "f2": 4448.01,
      "f3": 1.19,
      "f4": 52.42,
      "f5": 102944968,
      "f6": 263883567968.0,
      "f12": "BK0854",
      "f14": "华为概念",
      "f20": 19409476864000,
      "f62": 2464383488.0,
      "f66": 3308802560.0,
      "f69": 1.26,
      "f72": -844419072.0,
      "f75": -0.32,
      "f78": -4002119680.0,
      "f81": -1.52,
      "f84": 1586325504.0,
      "f87": 0.6,
      "f104": 570,
      "f105": 159,
      "f184": 0.93
    },
    {
      "f2": 994.27,
      "f3": 2.43,
      "f4": 23.56,
      "f5": 16598296,
      "f6": 75254007091.0,
      "f12": "BK1710",
      "f14": "先进制造风格",
      "f20": 11590901504000,
      "f62": 2437751296.0,
      "f66": 1632193536.0,
      "f69": 2.17,
      "f72": 805557760.0,
      "f75": 1.07,
      "f78": -1450477312.0,
      "f81": -1.93,
      "f84": -986647552.0,
      "f87": -1.31,
      "f104": 88,
      "f105": 11,
      "f184": 3.24
    },
    {
      "f2": 2677.23,
      "f3": 2.25,
      "f4": 58.87,
      "f5": 36905707,
      "f6": 112990865121.0,
      "f12": "BK0963",
      "f14": "商业航天",
      "f20": 6485622528000,
      "f62": 2428647936.0,
      "f66": 2220804352.0,
      "f69": 1.97,
      "f72": 207843584.0,
      "f75": 0.18,
      "f78": -1260772096.0,
      "f81": -1.12,
      "f84": -1119213312.0,
      "f87": -0.99,
      "f104": 247,
      "f105": 52,
      "f184": 2.15
    },
    {
      "f2": 2750.12,
      "f3": 2.35,
      "f4": 63.23,
      "f5": 23344777,
      "f6": 55352159006.0,
      "f12": "BK0704",
      "f14": "无人机",
      "f20": 3855265280000,
      "f62": 2331563008.0,
      "f66": 1785278976.0,
      "f69": 3.23,
      "f72": 546284032.0,
      "f75": 0.99,
      "f78": -1229998080.0,
      "f81": -2.22,
      "f84": -1115586304.0,
      "f87": -2.02,
      "f104": 184,
      "f105": 31,
      "f184": 4.22
    },
    {
      "f2": 1689.73,
      "f3": 2.31,
      "f4": 38.13,
      "f5": 27086994,
      "f6": 58987675712.0,
      "f12": "BK1166",
      "f14": "低空经济",
      "f20": 4412711680000,
      "f62": 2205127424.0,
      "f66": 2352602880.0,
      "f69": 3.99,
      "f72": -147475456.0,
      "f75": -0.25,
      "f78": -1512924416.0,
      "f81": -2.57,
      "f84": -663224832.0,
      "f87": -1.13,
      "f104": 248,
      "f105": 40,
      "f184": 3.74
    },
    {
      "f2": 1762.73,
      "f3": 1.37,
      "f4": 23.74,
      "f5": 17628145,
      "f6": 55647498137.0,
      "f12": "BK1104",
      "f14": "信创",
      "f20": 4217788384000,
      "f62": 2159660288.0,
      "f66": 1854858240.0,
      "f69": 3.33,
      "f72": 304802048.0,
      "f75": 0.55,
      "f78": -2699783168.0,
      "f81": -4.85,
      "f84": 548967424.0,
      "f87": 0.99,
      "f104": 205,
      "f105": 34,
      "f184": 3.88
    },
    {
      "f2": 4594.75,
      "f3": 0.69,
      "f4": 31.64,
      "f5": 42231829,
      "f6": 118183675623.0,
      "f12": "BK0840",
      "f14": "OLED",
      "f20": 4633236480000,
      "f62": 1960093696.0,
      "f66": 2521809664.0,
      "f69": 2.14,
      "f72": -561715968.0,
      "f75": -0.48,
      "f78": -1998069504.0,
      "f81": -1.69,
      "f84": 44900864.0,
      "f87": 0.04,
      "f104": 71,
      "f105": 54,
      "f184": 1.66
    },
    {
      "f2": 1776.26,
      "f3": 1.41,
      "f4": 24.74,
      "f5": 64489833,
      "f6": 139830854433.0,
      "f12": "BK0800",
      "f14": "人工智能",
      "f20": 14348366848000,
      "f62": 1952311808.0,
      "f66": 2293709568.0,
      "f69": 1.64,
      "f72": -341397760.0,
      "f75": -0.24,
      "f78": -3225587712.0,
      "f81": -2.31,
      "f84": 1299991808.0,
      "f87": 0.93,
      "f104": 582,
      "f105": 110,
      "f184": 1.4
    },
    {
      "f2": 2463.0,
      "f3": 1.67,
      "f4": 40.36,
      "f5": 12672381,
      "f6": 114745071519.0,
      "f12": "BK0638",
      "f14": "创业成份",
      "f20": 10299807488000,
      "f62": 1944589312.0,
      "f66": 3218481664.0,
      "f69": 2.8,
      "f72": -1273892352.0,
      "f75": -1.11,
      "f78": -1555058176.0,
      "f81": -1.36,
      "f84": -389531136.0,
      "f87": -0.34,
      "f104": 80,
      "f105": 17,
      "f184": 1.69
    },
    {
      "f2": 4387.67,
      "f3": 0.95,
      "f4": 41.25,
      "f5": 27881438,
      "f6": 81553560308.0,
      "f12": "BK0641",
      "f14": "智能穿戴",
      "f20": 4363684352000,
      "f62": 1900179968.0,
      "f66": 2284331776.0,
      "f69": 2.8,
      "f72": -384151808.0,
      "f75": -0.47,
      "f78": -2751161856.0,
      "f81": -3.38,
      "f84": 846288384.0,
      "f87": 1.04,
      "f104": 92,
      "f105": 33,
      "f184": 2.33
    },
    {
      "f2": 7312.45,
      "f3": 1.31,
      "f4": 94.47,
      "f5": 24502837,
      "f6": 79963373598.0,
      "f12": "BK0644",
      "f14": "特斯拉概念",
      "f20": 7322694912000,
      "f62": 1866439680.0,
      "f66": 2220667904.0,
      "f69": 2.78,
      "f72": -354228224.0,
      "f75": -0.44,
      "f78": -1703386624.0,
      "f81": -2.13,
      "f84": -154338560.0,
      "f87": -0.19,
      "f104": 165,
      "f105": 45,
      "f184": 2.33
    },
    {
      "f2": 5379.12,
      "f3": 0.75,
      "f4": 39.78,
      "f5": 13254971,
      "f6": 71769575807.0,
      "f12": "BK0884",
      "f14": "光刻机(胶)",
      "f20": 2509130752000,
      "f62": 1764607232.0,
      "f66": 1481196032.0,
      "f69": 2.06,
      "f72": 283411200.0,
      "f75": 0.4,
      "f78": -1352612608.0,
      "f81": -1.89,
      "f84": -386604288.0,
      "f87": -0.54,
      "f104": 52,
      "f105": 43,
      "f184": 2.46
    },
    {
      "f2": 2634.43,
      "f3": 1.22,
      "f4": 31.78,
      "f5": 11213402,
      "f6": 47686234468.0,
      "f12": "BK0893",
      "f14": "无线耳机",
      "f20": 3372817936000,
      "f62": 1712220160.0,
      "f66": 1725105664.0,
      "f69": 3.62,
      "f72": -12885504.0,
      "f75": -0.03,
      "f78": -1710283520.0,
      "f81": -3.59,
      "f84": -925440.0,
      "f87": 0.0,
      "f104": 68,
      "f105": 12,
      "f184": 3.59
    },
    {
      "f2": 2334.06,
      "f3": 1.66,
      "f4": 38.17,
      "f5": 6800907,
      "f6": 38011175644.0,
      "f12": "BK1161",
      "f14": "英伟达概念",
      "f20": 3728494560000,
      "f62": 1710110976.0,
      "f66": 1561245952.0,
      "f69": 4.11,
      "f72": 148865024.0,
      "f75": 0.39,
      "f78": -1109648384.0,
      "f81": -2.92,
      "f84": -587317760.0,
      "f87": -1.55,
      "f104": 50,
      "f105": 9,
      "f184": 4.5
    },
    {
      "f2": 981.78,
      "f3": 1.11,
      "f4": 10.81,
      "f5": 78101326,
      "f6": 193350090196.0,
      "f12": "BK1648",
      "f14": "电池技术",
      "f20": 15443877120000,
      "f62": 1692421888.0,
      "f66": 1665158656.0,
      "f69": 0.86,
      "f72": 27263232.0,
      "f75": 0.01,
      "f78": -2449250048.0,
      "f81": -1.27,
      "f84": 745996032.0,
      "f87": 0.39,
      "f104": 415,
      "f105": 148,
      "f184": 0.88
    },
    {
      "f2": 2050.42,
      "f3": 1.1,
      "f4": 22.31,
      "f5": 18464388,
      "f6": 56721940816.0,
      "f12": "BK0611",
      "f14": "上证50_",
      "f20": 27718208512000,
      "f62": 1655162368.0,
      "f66": 1276267520.0,
      "f69": 2.25,
      "f72": 378894848.0,
      "f75": 0.67,
      "f78": -1710578944.0,
      "f81": -3.02,
      "f84": 55617536.0,
      "f87": 0.1,
      "f104": 38,
      "f105": 11,
      "f184": 2.92
    },
    {
      "f2": 1321.75,
      "f3": 1.02,
      "f4": 13.41,
      "f5": 30586894,
      "f6": 114925006147.0,
      "f12": "BK0743",
      "f14": "深证100R",
      "f20": 17469372160000,
      "f62": 1608123136.0,
      "f66": 3111407104.0,
      "f69": 2.71,
      "f72": -1503283968.0,
      "f75": -1.31,
      "f78": -1633849088.0,
      "f81": -1.42,
      "f84": 25725696.0,
      "f87": 0.02,
      "f104": 73,
      "f105": 24,
      "f184": 1.4
    },
    {
      "f2": 4562.45,
      "f3": 1.17,
      "f4": 52.75,
      "f5": 56866821,
      "f6": 141841050897.0,
      "f12": "BK0574",
      "f14": "锂电池概念",
      "f20": 11875233536000,
      "f62": 1602916864.0,
      "f66": 1489176320.0,
      "f69": 1.05,
      "f72": 113740544.0,
      "f75": 0.08,
      "f78": -2342108928.0,
      "f81": -1.65,
      "f84": 725287680.0,
      "f87": 0.51,
      "f104": 297,
      "f105": 110,
      "f184": 1.13
    },
    {
      "f2": 1030.61,
      "f3": 0.92,
      "f4": 9.39,
      "f5": 17982609,
      "f6": 86250665569.0,
      "f12": "BK1662",
      "f14": "权重股",
      "f20": 41284960768000,
      "f62": 1593940992.0,
      "f66": 1965952768.0,
      "f69": 2.28,
      "f72": -372011776.0,
      "f75": -0.43,
      "f78": -1599091712.0,
      "f81": -1.86,
      "f84": 5378560.0,
      "f87": 0.01,
      "f104": 34,
      "f105": 15,
      "f184": 1.85
    },
    {
      "f2": 2577.29,
      "f3": 0.8,
      "f4": 20.57,
      "f5": 39009751,
      "f6": 84141120911.0,
      "f12": "BK0833",
      "f14": "小米概念",
      "f20": 5111240448000,
      "f62": 1573540352.0,
      "f66": 2098500864.0,
      "f69": 2.49,
      "f72": -524960512.0,
      "f75": -0.62,
      "f78": -2013513984.0,
      "f81": -2.39,
      "f84": 445538304.0,
      "f87": 0.53,
      "f104": 163,
      "f105": 61,
      "f184": 1.87
    },
    {
      "f2": 2535.16,
      "f3": 1.43,
      "f4": 35.69,
      "f5": 17553175,
      "f6": 46237660927.0,
      "f12": "BK0689",
      "f14": "阿里概念",
      "f20": 5088943104000,
      "f62": 1548862720.0,
      "f66": 1248629248.0,
      "f69": 2.7,
      "f72": 300233472.0,
      "f75": 0.65,
      "f78": -1563604736.0,
      "f81": -3.39,
      "f84": 17488640.0,
      "f87": 0.04,
      "f104": 144,
      "f105": 22,
      "f184": 3.36
    },
    {
      "f2": 1851.61,
      "f3": 1.73,
      "f4": 31.49,
      "f5": 23697881,
      "f6": 70614840843.0,
      "f12": "BK1184",
      "f14": "人形机器人",
      "f20": 6019052288000,
      "f62": 1541422336.0,
      "f66": 1664657664.0,
      "f69": 2.36,
      "f72": -123235328.0,
      "f75": -0.17,
      "f78": -1353543424.0,
      "f81": -1.92,
      "f84": -184190464.0,
      "f87": -0.26,
      "f104": 208,
      "f105": 37,
      "f184": 2.18
    },
    {
      "f2": 1007.18,
      "f3": 0.82,
      "f4": 8.16,
      "f5": 23560506,
      "f6": 26943116481.0,
      "f12": "BK1714",
      "f14": "金融地产风格",
      "f20": 22165572608000,
      "f62": 1344608000.0,
      "f66": 792978432.0,
      "f69": 2.95,
      "f72": 551629568.0,
      "f75": 2.05,
      "f78": -927811840.0,
      "f81": -3.45,
      "f84": -419096320.0,
      "f87": -1.56,
      "f104": 77,
      "f105": 19,
      "f184": 4.99
    },
    {
      "f2": 3700.26,
      "f3": 1.0,
      "f4": 36.74,
      "f5": 19613479,
      "f6": 65885096451.0,
      "f12": "BK0567",
      "f14": "股权激励",
      "f20": 5494251264000,
      "f62": 1332839424.0,
      "f66": 1269440000.0,
      "f69": 1.93,
      "f72": 63399424.0,
      "f75": 0.1,
      "f78": -1765126656.0,
      "f81": -2.68,
      "f84": 432814336.0,
      "f87": 0.66,
      "f104": 156,
      "f105": 49,
      "f184": 2.03
    },
    {
      "f2": 3046.32,
      "f3": 0.92,
      "f4": 27.7,
      "f5": 12775470,
      "f6": 35001121011.0,
      "f12": "BK0680",
      "f14": "智能家居",
      "f20": 4180527968000,
      "f62": 1321836032.0,
      "f66": 1072118784.0,
      "f69": 3.06,
      "f72": 249717248.0,
      "f75": 0.71,
      "f78": -896294912.0,
      "f81": -2.56,
      "f84": -423407360.0,
      "f87": -1.21,
      "f104": 119,
      "f105": 37,
      "f184": 3.78
    },
    {
      "f2": 58147.3,
      "f3": 5.51,
      "f4": 3035.09,
      "f5": 5657336,
      "f6": 15402966041.0,
      "f12": "BK0480",
      "f14": "航天航空",
      "f20": 1452215088000,
      "f62": 1312713920.0,
      "f66": 1074791792.0,
      "f69": 6.98,
      "f72": 237922128.0,
      "f75": 1.55,
      "f78": -406005504.0,
      "f81": -2.64,
      "f84": -895516720.0,
      "f87": -5.82,
      "f104": 51,
      "f105": 3,
      "f184": 8.53
    },
    {
      "f2": 16781.2,
      "f3": 1.08,
      "f4": 178.82,
      "f5": 44673412,
      "f6": 112084839811.0,
      "f12": "BK0554",
      "f14": "物联网",
      "f20": 11002733056000,
      "f62": 1286618112.0,
      "f66": 2017519104.0,
      "f69": 1.8,
      "f72": -730900992.0,
      "f75": -0.65,
      "f78": -2275735552.0,
      "f81": -2.03,
      "f84": 995885056.0,
      "f87": 0.89,
      "f104": 288,
      "f105": 81,
      "f184": 1.15
    },
    {
      "f2": 42355.31,
      "f3": 0.91,
      "f4": 380.27,
      "f5": 66353656,
      "f6": 172638221543.0,
      "f12": "BK0523",
      "f14": "新材料",
      "f20": 7840597248000,
      "f62": 1271687680.0,
      "f66": 1502882560.0,
      "f69": 0.87,
      "f72": -231194880.0,
      "f75": -0.13,
      "f78": -1508620800.0,
      "f81": -0.87,
      "f84": 194874880.0,
      "f87": 0.11,
      "f104": 257,
      "f105": 123,
      "f184": 0.74
    },
    {
      "f2": 2666.77,
      "f3": 1.6,
      "f4": 42.1,
      "f5": 18468664,
      "f6": 70556545783.0,
      "f12": "BK0952",
      "f14": "第三代半导体",
      "f20": 3413064736000,
      "f62": 1216002304.0,
      "f66": 1415257600.0,
      "f69": 2.01,
      "f72": -199255296.0,
      "f75": -0.28,
      "f78": -945204480.0,
      "f81": -1.34,
      "f84": -227635456.0,
      "f87": -0.32,
      "f104": 85,
      "f105": 22,
      "f184": 1.72
    },
    {
      "f2": 1310.87,
      "f3": 0.99,
      "f4": 12.86,
      "f5": 39468553,
      "f6": 58543556622.0,
      "f12": "BK0722",
      "f14": "虚拟现实",
      "f20": 4211603104000,
      "f62": 1204296192.0,
      "f66": 1438580224.0,
      "f69": 2.46,
      "f72": -234284032.0,
      "f75": -0.4,
      "f78": -1416517632.0,
      "f81": -2.42,
      "f84": 210958592.0,
      "f87": 0.36,
      "f104": 163,
      "f105": 51,
      "f184": 2.06
    },
    {
      "f2": 1066.09,
      "f3": 1.4,
      "f4": 14.77,
      "f5": 12814522,
      "f6": 38102205460.0,
      "f12": "BK1198",
      "f14": "2025三季报预增",
      "f20": 3855827840000,
      "f62": 1165148160.0,
      "f66": 1013314560.0,
      "f69": 2.66,
      "f72": 151833600.0,
      "f75": 0.4,
      "f78": -701201408.0,
      "f81": -1.84,
      "f84": -463646208.0,
      "f87": -1.22,
      "f104": 70,
      "f105": 19,
      "f184": 3.06
    },
    {
      "f2": 1565.12,
      "f3": 1.13,
      "f4": 17.54,
      "f5": 63946888,
      "f6": 88675521662.0,
      "f12": "BK0712",
      "f14": "一带一路",
      "f20": 16412963584000,
      "f62": 1134226688.0,
      "f66": 1219072000.0,
      "f69": 1.38,
      "f72": -84845312.0,
      "f75": -0.1,
      "f78": -1337618944.0,
      "f81": -1.51,
      "f84": 214684672.0,
      "f87": 0.24,
      "f104": 407,
      "f105": 86,
      "f184": 1.28
    },
    {
      "f2": 2009.86,
      "f3": 1.02,
      "f4": 20.2,
      "f5": 5105788,
      "f6": 25365389125.0,
      "f12": "BK1162",
      "f14": "AI手机",
      "f20": 1336843056000,
      "f62": 1120867328.0,
      "f66": 802842112.0,
      "f69": 3.17,
      "f72": 318025216.0,
      "f75": 1.25,
      "f78": -1624788224.0,
      "f81": -6.41,
      "f84": 503448624.0,
      "f87": 1.98,
      "f104": 23,
      "f105": 10,
      "f184": 4.42
    },
    {
      "f2": 5673.19,
      "f3": 4.25,
      "f4": 231.49,
      "f5": 9125598,
      "f6": 11608264057.0,
      "f12": "BK0625",
      "f14": "通用航空",
      "f20": 956832432000,
      "f62": 1112990560.0,
      "f66": 1206667824.0,
      "f69": 10.4,
      "f72": -93677264.0,
      "f75": -0.81,
      "f78": -525737552.0,
      "f81": -4.53,
      "f84": -586252864.0,
      "f87": -5.05,
      "f104": 33,
      "f105": 2,
      "f184": 9.59
    },
    {
      "f2": 1688.42,
      "f3": 1.23,
      "f4": 20.5,
      "f5": 15488841,
      "f6": 53706981632.0,
      "f12": "BK0823",
      "f14": "养老金",
      "f20": 5517472000000,
      "f62": 1061730560.0,
      "f66": 1103596800.0,
      "f69": 2.05,
      "f72": -41866240.0,
      "f75": -0.08,
      "f78": -988143616.0,
      "f81": -1.84,
      "f84": -73219072.0,
      "f87": -0.14,
      "f104": 157,
      "f105": 37,
      "f184": 1.98
    },
    {
      "f2": 12727.52,
      "f3": 1.21,
      "f4": 152.25,
      "f5": 25664881,
      "f6": 56524967839.0,
      "f12": "BK0528",
      "f14": "转债标的",
      "f20": 6178909952000,
      "f62": 1061095168.0,
      "f66": 564605440.0,
      "f69": 1.0,
      "f72": 496489728.0,
      "f75": 0.88,
      "f78": -1053004800.0,
      "f81": -1.86,
      "f84": -8040704.0,
      "f87": -0.01,
      "f104": 241,
      "f105": 71,
      "f184": 1.88
    },
    {
      "f2": 4430.66,
      "f3": 1.21,
      "f4": 52.96,
      "f5": 16655021,
      "f6": 41630555648.0,
      "f12": "BK0682",
      "f14": "燃料电池概念",
      "f20": 3403821536000,
      "f62": 1055928320.0,
      "f66": 1159987712.0,
      "f69": 2.79,
      "f72": -104059392.0,
      "f75": -0.25,
      "f78": -659280640.0,
      "f81": -1.58,
      "f84": -402490624.0,
      "f87": -0.97,
      "f104": 104,
      "f105": 33,
      "f184": 2.54
    },
    {
      "f2": 17300.3,
      "f3": 1.01,
      "f4": 173.63,
      "f5": 123559538,
      "f6": 207208011678.0,
      "f12": "BK0552",
      "f14": "机构重仓",
      "f20": 43999195648000,
      "f62": 1048355072.0,
      "f66": 1977729024.0,
      "f69": 0.96,
      "f72": -929373952.0,
      "f75": -0.45,
      "f78": -2332374016.0,
      "f81": -1.13,
      "f84": 1231478528.0,
      "f87": 0.59,
      "f104": 853,
      "f105": 249,
      "f184": 0.51
    },
    {
      "f2": 2903.19,
      "f3": 1.28,
      "f4": 36.76,
      "f5": 47717998,
      "f6": 127091087036.0,
      "f12": "BK0705",
      "f14": "上证380",
      "f20": 12029897984000,
      "f62": 1041423872.0,
      "f66": 972798464.0,
      "f69": 0.77,
      "f72": 68625408.0,
      "f75": 0.05,
      "f78": -2417724416.0,
      "f81": -1.9,
      "f84": 1380644352.0,
      "f87": 1.09,
      "f104": 294,
      "f105": 78,
      "f184": 0.82
    },
    {
      "f2": 2319.97,
      "f3": 1.64,
      "f4": 37.54,
      "f5": 11187104,
      "f6": 38919679723.0,
      "f12": "BK0905",
      "f14": "传感器",
      "f20": 2596788784000,
      "f62": 1037034496.0,
      "f66": 932883968.0,
      "f69": 2.4,
      "f72": 104150528.0,
      "f75": 0.27,
      "f78": -1151678464.0,
      "f81": -2.96,
      "f84": 128662272.0,
      "f87": 0.33,
      "f104": 98,
      "f105": 24,
      "f184": 2.67
    },
    {
      "f2": 8758.01,
      "f3": 1.4,
      "f4": 120.88,
      "f5": 20507614,
      "f6": 28275178041.0,
      "f12": "BK0505",
      "f14": "中字头",
      "f20": 16010316288000,
      "f62": 970963328.0,
      "f66": 863476352.0,
      "f69": 3.06,
      "f72": 107486976.0,
      "f75": 0.38,
      "f78": -608346880.0,
      "f81": -2.15,
      "f84": -362245632.0,
      "f87": -1.28,
      "f104": 82,
      "f105": 15,
      "f184": 3.44
    },
    {
      "f2": 1955.46,
      "f3": 1.84,
      "f4": 35.34,
      "f5": 4192507,
      "f6": 13810400230.0,
      "f12": "BK1156",
      "f14": "PEEK材料概念",
      "f20": 957001248000,
      "f62": 954380784.0,
      "f66": 533673664.0,
      "f69": 3.87,
      "f72": 420707120.0,
      "f75": 3.05,
      "f78": -388705328.0,
      "f81": -2.82,
      "f84": -564918880.0,
      "f87": -4.09,
      "f104": 36,
      "f105": 8,
      "f184": 6.92
    },
    {
      "f2": 1350.25,
      "f3": 0.83,
      "f4": 11.12,
      "f5": 39356794,
      "f6": 64613377130.0,
      "f12": "BK0718",
      "f14": "证金持股",
      "f20": 32981302016000,
      "f62": 933326080.0,
      "f66": 721179392.0,
      "f69": 1.12,
      "f72": 212146688.0,
      "f75": 0.33,
      "f78": -1216453632.0,
      "f81": -1.88,
      "f84": 283812096.0,
      "f87": 0.44,
      "f104": 144,
      "f105": 36,
      "f184": 1.45
    },
    {
      "f2": 4646.22,
      "f3": 1.47,
      "f4": 67.13,
      "f5": 9557723,
      "f6": 23877089821.0,
      "f12": "BK0674",
      "f14": "蓝宝石",
      "f20": 910929888000,
      "f62": 891990784.0,
      "f66": 1207939072.0,
      "f69": 5.07,
      "f72": -315948288.0,
      "f75": -1.33,
      "f78": -774337024.0,
      "f81": -3.25,
      "f84": -117648128.0,
      "f87": -0.49,
      "f104": 14,
      "f105": 4,
      "f184": 3.74
    },
    {
      "f2": 932.32,
      "f3": 1.55,
      "f4": 14.2,
      "f5": 5053049,
      "f6": 12007598405.0,
      "f12": "BK1047",
      "f14": "数据安全",
      "f20": 1132825152000,
      "f62": 876810960.0,
      "f66": 980951440.0,
      "f69": 8.17,
      "f72": -104140480.0,
      "f75": -0.87,
      "f78": -616177056.0,
      "f81": -5.13,
      "f84": -259221280.0,
      "f87": -2.16,
      "f104": 71,
      "f105": 9,
      "f184": 7.3
    },
    {
      "f2": 932.72,
      "f3": 1.29,
      "f4": 11.88,
      "f5": 37420192,
      "f6": 87572443708.0,
      "f12": "BK1679",
      "f14": "2025年报扭亏",
      "f20": 5760768256000,
      "f62": 841713664.0,
      "f66": 1054566912.0,
      "f69": 1.21,
      "f72": -212853248.0,
      "f75": -0.24,
      "f78": -1098599680.0,
      "f81": -1.26,
      "f84": 263104512.0,
      "f87": 0.3,
      "f104": 276,
      "f105": 78,
      "f184": 0.96
    },
    {
      "f2": 1229.77,
      "f3": 1.29,
      "f4": 15.69,
      "f5": 22289733,
      "f6": 46425515293.0,
      "f12": "BK1188",
      "f14": "DeepSeek概念",
      "f20": 4641728512000,
      "f62": 834944000.0,
      "f66": 602882560.0,
      "f69": 1.3,
      "f72": 232061440.0,
      "f75": 0.5,
      "f78": -991431168.0,
      "f81": -2.14,
      "f84": 161916416.0,
      "f87": 0.35,
      "f104": 224,
      "f105": 28,
      "f184": 1.8
    },
    {
      "f2": 1001.44,
      "f3": 1.04,
      "f4": 10.28,
      "f5": 10093503,
      "f6": 12643105127.0,
      "f12": "BK0711",
      "f14": "券商概念",
      "f20": 3647026224000,
      "f62": 824079584.0,
      "f66": 575875200.0,
      "f69": 4.56,
      "f72": 248204384.0,
      "f75": 1.97,
      "f78": -519293776.0,
      "f81": -4.11,
      "f84": -307304784.0,
      "f87": -2.43,
      "f104": 47,
      "f105": 7,
      "f184": 6.53
    },
    {
      "f2": 2860.51,
      "f3": 1.07,
      "f4": 30.42,
      "f5": 6075479,
      "f6": 25203950639.0,
      "f12": "BK0865",
      "f14": "电子烟",
      "f20": 1596805728000,
      "f62": 812518144.0,
      "f66": 769547520.0,
      "f69": 3.05,
      "f72": 42970624.0,
      "f75": 0.17,
      "f78": -557946880.0,
      "f81": -2.21,
      "f84": -254266112.0,
      "f87": -1.01,
      "f104": 41,
      "f105": 11,
      "f184": 3.23
    },
    {
      "f2": 2159.06,
      "f3": 2.23,
      "f4": 47.17,
      "f5": 13545330,
      "f6": 43559718288.0,
      "f12": "BK0921",
      "f14": "卫星互联网",
      "f20": 2834150784000,
      "f62": 771990528.0,
      "f66": 400512000.0,
      "f69": 0.92,
      "f72": 371478528.0,
      "f75": 0.85,
      "f78": -68474112.0,
      "f81": -0.16,
      "f84": -683783936.0,
      "f87": -1.57,
      "f104": 79,
      "f105": 13,
      "f184": 1.77
    },
    {
      "f2": 40325.91,
      "f3": 0.94,
      "f4": 373.85,
      "f5": 36919375,
      "f6": 86285921204.0,
      "f12": "BK0549",
      "f14": "深圳特区",
      "f20": 11448246272000,
      "f62": 766458624.0,
      "f66": 687198720.0,
      "f69": 0.8,
      "f72": 79259904.0,
      "f75": 0.09,
      "f78": -930175744.0,
      "f81": -1.08,
      "f84": 176256512.0,
      "f87": 0.2,
      "f104": 251,
      "f105": 82,
      "f184": 0.89
    },
    {
      "f2": 2419.27,
      "f3": 1.09,
      "f4": 26.11,
      "f5": 50779215,
      "f6": 100520521666.0,
      "f12": "BK0989",
      "f14": "储能概念",
      "f20": 12561633792000,
      "f62": 744155904.0,
      "f66": 932717568.0,
      "f69": 0.93,
      "f72": -188561664.0,
      "f75": -0.19,
      "f78": -1706195968.0,
      "f81": -1.7,
      "f84": 947918080.0,
      "f87": 0.94,
      "f104": 343,
      "f105": 99,
      "f184": 0.74
    },
    {
      "f2": 609.26,
      "f3": 0.99,
      "f4": 6.0,
      "f5": 4119437,
      "f6": 26801486040.0,
      "f12": "BK1000",
      "f14": "宁组合",
      "f20": 5210516480000,
      "f62": 741297920.0,
      "f66": 1389386496.0,
      "f69": 5.19,
      "f72": -648088576.0,
      "f75": -2.42,
      "f78": -1158799360.0,
      "f81": -4.33,
      "f84": 417627600.0,
      "f87": 1.56,
      "f104": 19,
      "f105": 5,
      "f184": 2.77
    },
    {
      "f2": 1324.4,
      "f3": 1.72,
      "f4": 22.39,
      "f5": 2967480,
      "f6": 17520737651.0,
      "f12": "BK1108",
      "f14": "科创板做市股",
      "f20": 2388905104000,
      "f62": 706592608.0,
      "f66": 641025376.0,
      "f69": 3.66,
      "f72": 65567232.0,
      "f75": 0.37,
      "f78": -627636992.0,
      "f81": -3.59,
      "f84": -78463264.0,
      "f87": -0.45,
      "f104": 38,
      "f105": 6,
      "f184": 4.04
    },
    {
      "f2": 697.52,
      "f3": 1.0,
      "f4": 6.92,
      "f5": 5949004,
      "f6": 36478575313.0,
      "f12": "BK0999",
      "f14": "茅指数",
      "f20": 13266490112000,
      "f62": 699486976.0,
      "f66": 968308224.0,
      "f69": 2.66,
      "f72": -268821248.0,
      "f75": -0.74,
      "f78": -890545152.0,
      "f81": -2.44,
      "f84": 191132160.0,
      "f87": 0.52,
      "f104": 34,
      "f105": 8,
      "f184": 1.92
    },
    {
      "f2": 1892.47,
      "f3": 2.95,
      "f4": 54.21,
      "f5": 13762795,
      "f6": 28213355910.0,
      "f12": "BK0814",
      "f14": "大飞机",
      "f20": 2121271552000,
      "f62": 641758224.0,
      "f66": 578739472.0,
      "f69": 2.05,
      "f72": 63018752.0,
      "f75": 0.22,
      "f78": -289808128.0,
      "f81": -1.03,
      "f84": -367842048.0,
      "f87": -1.3,
      "f104": 86,
      "f105": 14,
      "f184": 2.28
    },
    {
      "f2": 979.87,
      "f3": 0.55,
      "f4": 5.33,
      "f5": 29597379,
      "f6": 115256823791.0,
      "f12": "BK1715",
      "f14": "趋势股",
      "f20": 9636039424000,
      "f62": 638059520.0,
      "f66": 661691904.0,
      "f69": 0.57,
      "f72": -23632384.0,
      "f75": -0.02,
      "f78": -1222568704.0,
      "f81": -1.06,
      "f84": 454790912.0,
      "f87": 0.39,
      "f104": 65,
      "f105": 59,
      "f184": 0.55
    },
    {
      "f2": 3410.09,
      "f3": 1.18,
      "f4": 39.64,
      "f5": 60486403,
      "f6": 117760488738.0,
      "f12": "BK0590",
      "f14": "西部大开发",
      "f20": 13061236224000,
      "f62": 630349312.0,
      "f66": 1683424256.0,
      "f69": 1.43,
      "f72": -1053074944.0,
      "f75": -0.89,
      "f78": -728115456.0,
      "f81": -0.62,
      "f84": 122380800.0,
      "f87": 0.1,
      "f104": 464,
      "f105": 126,
      "f184": 0.54
    }
  ],
  "capital_flow_top30": [
    {
      "f2": 352.4,
      "f3": 8.67,
      "f6": 7991502443.0,
      "f7": 6.35,
      "f8": 4.85,
      "f12": "688525",
      "f14": "佰维存储",
      "f62": 917203696.0,
      "f66": 666486480.0,
      "f69": 8.34,
      "f72": 250717216.0,
      "f75": 3.14,
      "f78": -896468944.0,
      "f81": -11.22,
      "f84": -20664309.0,
      "f87": -0.26,
      "f184": 11.48
    },
    {
      "f2": 498.72,
      "f3": 3.15,
      "f6": 8500339538.0,
      "f7": 2.34,
      "f8": 2.52,
      "f12": "603986",
      "f14": "兆易创新",
      "f62": 849770288.0,
      "f66": 966325248.0,
      "f69": 11.37,
      "f72": -116554960.0,
      "f75": -1.37,
      "f78": -849509136.0,
      "f81": -10.0,
      "f84": -211284.0,
      "f87": 0.0,
      "f184": 10.0
    },
    {
      "f2": 339.49,
      "f3": 4.3,
      "f6": 6048045360.74,
      "f7": 4.0,
      "f8": 2.04,
      "f12": "300476",
      "f14": "胜宏科技",
      "f62": 784690752.0,
      "f66": 825489344.0,
      "f69": 13.65,
      "f72": -40798592.0,
      "f75": -0.67,
      "f78": -416813920.0,
      "f81": -6.89,
      "f84": -367876848.0,
      "f87": -6.08,
      "f184": 12.98
    },
    {
      "f2": 547.6,
      "f3": 6.37,
      "f6": 4337594666.0,
      "f7": 3.99,
      "f8": 2.83,
      "f12": "301308",
      "f14": "江波龙",
      "f62": 707819712.0,
      "f66": 545836352.0,
      "f69": 12.59,
      "f72": 161983360.0,
      "f75": 3.74,
      "f78": -707750032.0,
      "f81": -16.32,
      "f84": -69678.0,
      "f87": 0.0,
      "f184": 16.32
    },
    {
      "f2": 20.65,
      "f3": 10.02,
      "f6": 1524473446.07,
      "f7": 8.84,
      "f8": 4.72,
      "f12": "000547",
      "f14": "航天发展",
      "f62": 583200183.0,
      "f66": 648986135.0,
      "f69": 42.57,
      "f72": -65785952.0,
      "f75": -4.32,
      "f78": -280446484.0,
      "f81": -18.4,
      "f84": -302753693.0,
      "f87": -19.86,
      "f184": 38.26
    },
    {
      "f2": 193.67,
      "f3": 6.32,
      "f6": 3281693993.79,
      "f7": 4.9,
      "f8": 3.82,
      "f12": "300475",
      "f14": "香农芯创",
      "f62": 551779040.0,
      "f66": 206938144.0,
      "f69": 6.31,
      "f72": 344840896.0,
      "f75": 10.51,
      "f78": -172702720.0,
      "f81": -5.26,
      "f84": -379076336.0,
      "f87": -11.55,
      "f184": 16.81
    },
    {
      "f2": 42.94,
      "f3": 4.55,
      "f6": 3544478649.0,
      "f7": 5.06,
      "f8": 2.05,
      "f12": "600176",
      "f14": "中国巨石",
      "f62": 540898992.0,
      "f66": 382050144.0,
      "f69": 10.78,
      "f72": 158848848.0,
      "f75": 4.48,
      "f78": -206055744.0,
      "f81": -5.81,
      "f84": -334869008.0,
      "f87": -9.45,
      "f184": 15.26
    },
    {
      "f2": 671.07,
      "f3": 5.27,
      "f6": 4587236011.63,
      "f7": 3.14,
      "f8": 0.94,
      "f12": "002371",
      "f14": "北方华创",
      "f62": 469410608.0,
      "f66": 583827616.0,
      "f69": 12.73,
      "f72": -114417008.0,
      "f75": -2.49,
      "f78": -469259248.0,
      "f81": -10.23,
      "f84": -151366.0,
      "f87": 0.0,
      "f184": 10.23
    },
    {
      "f2": 216.79,
      "f3": 2.75,
      "f6": 5172405843.54,
      "f7": 3.31,
      "f8": 1.72,
      "f12": "002384",
      "f14": "东山精密",
      "f62": 464172128.0,
      "f66": 572139120.0,
      "f69": 11.06,
      "f72": -107966992.0,
      "f75": -2.09,
      "f78": -311961936.0,
      "f81": -6.03,
      "f84": -152210176.0,
      "f87": -2.94,
      "f184": 8.98
    },
    {
      "f2": 315.53,
      "f3": 4.09,
      "f6": 5033347965.0,
      "f7": 3.67,
      "f8": 1.68,
      "f12": "688012",
      "f14": "中微公司",
      "f62": 447403072.0,
      "f66": 545476656.0,
      "f69": 10.84,
      "f72": -98073584.0,
      "f75": -1.95,
      "f78": -434779872.0,
      "f81": -8.64,
      "f84": -11135470.0,
      "f87": -0.22,
      "f184": 8.89
    },
    {
      "f2": 10.55,
      "f3": 4.15,
      "f6": 2733241563.41,
      "f7": 7.7,
      "f8": 6.22,
      "f12": "002129",
      "f14": "TCL中环",
      "f62": 401103328.0,
      "f66": 476441760.0,
      "f69": 17.44,
      "f72": -75338432.0,
      "f75": -2.76,
      "f78": -210182048.0,
      "f81": -7.69,
      "f84": -190921280.0,
      "f87": -6.99,
      "f184": 14.68
    },
    {
      "f2": 154.09,
      "f3": 2.91,
      "f6": 5728137104.0,
      "f7": 5.76,
      "f8": 1.51,
      "f12": "600183",
      "f14": "生益科技",
      "f62": 388186992.0,
      "f66": 302640832.0,
      "f69": 5.3,
      "f72": 85546160.0,
      "f75": 1.5,
      "f78": -171921264.0,
      "f81": -3.01,
      "f84": -216234912.0,
      "f87": -3.78,
      "f184": 6.79
    },
    {
      "f2": 44.36,
      "f3": 3.94,
      "f6": 5084171948.25,
      "f7": 8.32,
      "f8": 2.24,
      "f12": "300433",
      "f14": "蓝思科技",
      "f62": 373562768.0,
      "f66": 398645184.0,
      "f69": 7.84,
      "f72": -25082416.0,
      "f75": -0.49,
      "f78": -197815648.0,
      "f81": -3.89,
      "f84": -175747136.0,
      "f87": -3.46,
      "f184": 7.35
    },
    {
      "f2": 413.97,
      "f3": 6.81,
      "f6": 1599687792.0,
      "f7": 5.03,
      "f8": 2.6,
      "f12": "688766",
      "f14": "普冉股份",
      "f62": 344092141.0,
      "f66": 257119325.0,
      "f69": 16.13,
      "f72": 86972816.0,
      "f75": 5.46,
      "f78": -342466944.0,
      "f81": -21.48,
      "f84": -1625195.0,
      "f87": -0.1,
      "f184": 21.59
    },
    {
      "f2": 657.99,
      "f3": 4.05,
      "f6": 3389891796.74,
      "f7": 2.45,
      "f8": 3.12,
      "f12": "001309",
      "f14": "德明利",
      "f62": 339533808.0,
      "f66": 314772880.0,
      "f69": 9.29,
      "f72": 24760928.0,
      "f75": 0.73,
      "f78": -339349024.0,
      "f81": -10.01,
      "f84": -184780.0,
      "f87": -0.01,
      "f184": 10.02
    },
    {
      "f2": 9.28,
      "f3": 9.95,
      "f6": 1055389883.0,
      "f7": 6.4,
      "f8": 2.29,
      "f12": "600497",
      "f14": "驰宏锌锗",
      "f62": 325369654.0,
      "f66": 334809107.0,
      "f69": 31.72,
      "f72": -9439453.0,
      "f75": -0.89,
      "f78": -183260505.0,
      "f81": -17.36,
      "f84": -142109153.0,
      "f87": -13.47,
      "f184": 30.83
    },
    {
      "f2": 689.0,
      "f3": 5.15,
      "f6": 3519837542.0,
      "f7": 5.32,
      "f8": 1.78,
      "f12": "688072",
      "f14": "拓荆科技",
      "f62": 322485072.0,
      "f66": 210877824.0,
      "f69": 5.99,
      "f72": 111607248.0,
      "f75": 3.17,
      "f78": -319819808.0,
      "f81": -9.09,
      "f84": -2389763.0,
      "f87": -0.07,
      "f184": 9.16
    },
    {
      "f2": 24.46,
      "f3": 9.98,
      "f6": 771463115.7,
      "f7": 5.85,
      "f8": 3.06,
      "f12": "000969",
      "f14": "安泰科技",
      "f62": 305805188.0,
      "f66": 392744211.0,
      "f69": 50.91,
      "f72": -86939023.0,
      "f75": -11.27,
      "f78": -169479554.0,
      "f81": -21.97,
      "f84": -136325629.0,
      "f87": -17.67,
      "f184": 39.64
    },
    {
      "f2": 128.42,
      "f3": 1.19,
      "f6": 4462051661.99,
      "f7": 4.96,
      "f8": 1.76,
      "f12": "002463",
      "f14": "沪电股份",
      "f62": 282283616.0,
      "f66": 93958224.0,
      "f69": 2.11,
      "f72": 188325392.0,
      "f75": 4.22,
      "f78": -63541408.0,
      "f81": -1.43,
      "f84": -218742208.0,
      "f87": -4.91,
      "f184": 6.33
    },
    {
      "f2": 22.84,
      "f3": 10.02,
      "f6": 1906631262.36,
      "f7": 7.71,
      "f8": 9.53,
      "f12": "001696",
      "f14": "宗申动力",
      "f62": 259610342.0,
      "f66": 371776998.0,
      "f69": 19.5,
      "f72": -112166656.0,
      "f75": -5.88,
      "f78": -173542592.0,
      "f81": -9.1,
      "f84": -86067760.0,
      "f87": -4.51,
      "f184": 13.62
    },
    {
      "f2": 229.8,
      "f3": 5.2,
      "f6": 1869102084.53,
      "f7": 6.18,
      "f8": 1.69,
      "f12": "300857",
      "f14": "协创数据",
      "f62": 254712736.0,
      "f66": 225565024.0,
      "f69": 12.07,
      "f72": 29147712.0,
      "f75": 1.56,
      "f78": -100057072.0,
      "f81": -5.35,
      "f84": -154655680.0,
      "f87": -8.27,
      "f184": 13.63
    },
    {
      "f2": 181.1,
      "f3": 9.1,
      "f6": 1961342385.65,
      "f7": 12.99,
      "f8": 7.91,
      "f12": "301396",
      "f14": "宏景科技",
      "f62": 246483536.0,
      "f66": 157285856.0,
      "f69": 8.02,
      "f72": 89197680.0,
      "f75": 4.55,
      "f78": -90582960.0,
      "f81": -4.62,
      "f84": -155900592.0,
      "f87": -7.95,
      "f184": 12.57
    },
    {
      "f2": 28.2,
      "f3": 3.18,
      "f6": 3364474933.0,
      "f7": 1.65,
      "f8": 0.58,
      "f12": "601899",
      "f14": "紫金矿业",
      "f62": 244723568.0,
      "f66": -99020752.0,
      "f69": -2.94,
      "f72": 343744320.0,
      "f75": 10.22,
      "f78": -141698864.0,
      "f81": -4.21,
      "f84": -103030368.0,
      "f87": -3.06,
      "f184": 7.27
    },
    {
      "f2": 13.59,
      "f3": 10.04,
      "f6": 912064244.43,
      "f7": 9.55,
      "f8": 3.25,
      "f12": "002085",
      "f14": "万丰奥威",
      "f62": 240762578.0,
      "f66": 234057072.0,
      "f69": 25.66,
      "f72": 6705506.0,
      "f75": 0.74,
      "f78": -103655557.0,
      "f81": -11.36,
      "f84": -137107032.0,
      "f87": -15.03,
      "f184": 26.4
    },
    {
      "f2": 6.73,
      "f3": 4.34,
      "f6": 1498469964.7,
      "f7": 5.58,
      "f8": 2.0,
      "f12": "000630",
      "f14": "铜陵有色",
      "f62": 234746123.0,
      "f66": 76832939.0,
      "f69": 5.13,
      "f72": 157913184.0,
      "f75": 10.55,
      "f78": -57890688.0,
      "f81": -3.87,
      "f84": -176855450.0,
      "f87": -11.81,
      "f184": 15.68
    },
    {
      "f2": 119.4,
      "f3": 8.45,
      "f6": 1505261272.35,
      "f7": 5.45,
      "f8": 8.72,
      "f12": "301611",
      "f14": "珂玛科技",
      "f62": 231304109.0,
      "f66": 128549581.0,
      "f69": 8.54,
      "f72": 102754528.0,
      "f75": 6.83,
      "f78": -132898048.0,
      "f81": -8.83,
      "f84": -98406074.0,
      "f87": -6.54,
      "f184": 15.37
    },
    {
      "f2": 86.4,
      "f3": 14.47,
      "f6": 3547130125.08,
      "f7": 6.56,
      "f8": 5.53,
      "f12": "300054",
      "f14": "鼎龙股份",
      "f62": 228600576.0,
      "f66": 266627232.0,
      "f69": 7.52,
      "f72": -38026656.0,
      "f75": -1.07,
      "f78": -184549808.0,
      "f81": -5.21,
      "f84": -44050752.0,
      "f87": -1.24,
      "f184": 6.45
    },
    {
      "f2": 51.74,
      "f3": 9.99,
      "f6": 722656272.0,
      "f7": 5.74,
      "f8": 3.67,
      "f12": "603738",
      "f14": "泰晶科技",
      "f62": 227464440.0,
      "f66": 313704575.0,
      "f69": 43.41,
      "f72": -86240135.0,
      "f75": -11.93,
      "f78": -123467968.0,
      "f81": -17.09,
      "f84": -103996475.0,
      "f87": -14.39,
      "f184": 31.48
    },
    {
      "f2": 93.28,
      "f3": 10.0,
      "f6": 2055446120.55,
      "f7": 7.5,
      "f8": 3.1,
      "f12": "002636",
      "f14": "金安国纪",
      "f62": 224974592.0,
      "f66": 255881712.0,
      "f69": 12.45,
      "f72": -30907120.0,
      "f75": -1.5,
      "f78": -138861824.0,
      "f81": -6.76,
      "f84": -86112762.0,
      "f87": -4.19,
      "f184": 10.95
    },
    {
      "f2": 236.35,
      "f3": 3.34,
      "f6": 5049842331.0,
      "f7": 3.81,
      "f8": 1.83,
      "f12": "688008",
      "f14": "澜起科技",
      "f62": 224629440.0,
      "f66": 325949360.0,
      "f69": 6.45,
      "f72": -101319920.0,
      "f75": -2.01,
      "f78": -217539280.0,
      "f81": -4.31,
      "f84": -7032732.0,
      "f87": -0.14,
      "f184": 4.45
    }
  ]
}